digibase.py
digibase-0.3.4.dist-info/licenses/LICENSE
digibase-0.3.4.dist-info/METADATA
digibase-0.3.4.dist-info/WHEEL
digibase-0.3.4.dist-info/top_level.txt
digibase-0.3.4.dist-info/RECORD
