Metadata-Version: 2.4
Name: digibase
Version: 0.3.4
Summary: Interface to ORTEC/AMETEK digital PMT base / Multichannel Scaler
Author-email: Kael Hanson <kael.hanson@gmail.com>
License: MIT
Project-URL: Repository, https://github.com/physkael/digiBase
Classifier: Development Status :: 3 - Alpha
Classifier: Intended Audience :: Science/Research
Classifier: License :: OSI Approved :: MIT License
Classifier: Programming Language :: Python :: 3
Classifier: Topic :: Scientific/Engineering :: Physics
Classifier: Operating System :: OS Independent
Requires-Python: >=3.8
License-File: LICENSE
Requires-Dist: numpy
Requires-Dist: pyusb
Dynamic: license-file
